queryandprocessdatautility/Classification.py
queryandprocessdatautility/IncentiveCalculation.py
queryandprocessdatautility/IntentClassification.py
queryandprocessdatautility/Outlier.py
queryandprocessdatautility/ProductIdentification.py
queryandprocessdatautility/ReadModelScopeFile.py
queryandprocessdatautility/SentimentAnalytics.py
queryandprocessdatautility/TimeSeriesForecasting.py
queryandprocessdatautility/TraineModel.py
queryandprocessdatautility/__init__.py
queryandprocessdatautility/autoarimaForecast.py
queryandprocessdatautility/autoetsForecast.py
queryandprocessdatautility/dartsForecasting.py
queryandprocessdatautility/prophetForecast.py
queryandprocessdatautility/pyaForecasting.py
queryandprocessdatautility-0.0.82.dist-info/LICENCE.txt
queryandprocessdatautility-0.0.82.dist-info/METADATA
queryandprocessdatautility-0.0.82.dist-info/WHEEL
queryandprocessdatautility-0.0.82.dist-info/top_level.txt
queryandprocessdatautility-0.0.82.dist-info/RECORD
