Metadata-Version: 2.1
Name: queryandprocessdatautility
Version: 0.0.82
Summary: Remove unnecessary log statements from the Python application logs.
Author: Proteus Technology PVT. LTD.
Author-email: <apps@baseinformation.com>
Keywords: python,first package
Classifier: Development Status :: 3 - Alpha
Classifier: Intended Audience :: Education
Classifier: Programming Language :: Python :: 2
Classifier: Programming Language :: Python :: 3
Classifier: Operating System :: MacOS :: MacOS X
Classifier: Operating System :: Microsoft :: Windows
License-File: LICENCE.txt
